{
  "dataOrgs":  {
    "orgs":  [
      {
        "orgId":  "123",
        "humanUsers":  [
          {
            "userId":  "auth0|6437e9c2b7add15a89b4915b",
            "user":  {
              "userName":  "test2@example.com",
              "profile":  {
                "firstName":  "Test Example2",
                "lastName":  "Test Example2"
              },
              "email":  {
                "email":  "test2@example.com",
                "isEmailVerified":  true
              },
              "hashedPassword":  {
                "value":  "$2b$10$Z6hUTEEeoJXN5/AmSm/4.eZ75RYgFVriQM9LPhNEC7kbAbS/VAaJ2"
              }
            }
          },
          {
            "userId":  "auth0|6437fa205c7266dc77f88a6c",
            "user":  {
              "userName":  "test@example.com",
              "profile":  {
                "firstName":  "Test User",
                "lastName":  "Test User"
              },
              "email":  {
                "email":  "test@example.com",
                "isEmailVerified":  true
              },
              "hashedPassword":  {
                "value":  "$2b$10$CSZ2JarG4XYbGa.JkfpqnO2wrlbfp5eb5LScHSGo9XGeZ.a.Ic54S"
              }
            }
          }
        ]
      }
    ]
  },
  "timeout":  "30m0s"
}
